jupyterlab_examples_hello_world/__init__.py
jupyterlab_examples_hello_world/_version.py
jupyterlab_examples_hello_world/labextension/package.json
jupyterlab_examples_hello_world/labextension/static/245.8a24fceaa29cae8adfd0.js
jupyterlab_examples_hello_world/labextension/static/568.fe0c39d0ae3e09e57bed.js
jupyterlab_examples_hello_world/labextension/static/remoteEntry.7186dfdad597778085bf.js
jupyterlab_examples_hello_world/labextension/static/style.js
jupyterlab_examples_hello_world/labextension/static/third-party-licenses.json
jupyterlab_examples_hello_world-0.1.0.data/data/share/jupyter/labextensions/@jupyterlab-examples/hello-world/install.json
jupyterlab_examples_hello_world-0.1.0.data/data/share/jupyter/labextensions/@jupyterlab-examples/hello-world/package.json
jupyterlab_examples_hello_world-0.1.0.data/data/share/jupyter/labextensions/@jupyterlab-examples/hello-world/static/245.8a24fceaa29cae8adfd0.js
jupyterlab_examples_hello_world-0.1.0.data/data/share/jupyter/labextensions/@jupyterlab-examples/hello-world/static/568.fe0c39d0ae3e09e57bed.js
jupyterlab_examples_hello_world-0.1.0.data/data/share/jupyter/labextensions/@jupyterlab-examples/hello-world/static/remoteEntry.7186dfdad597778085bf.js
jupyterlab_examples_hello_world-0.1.0.data/data/share/jupyter/labextensions/@jupyterlab-examples/hello-world/static/style.js
jupyterlab_examples_hello_world-0.1.0.data/data/share/jupyter/labextensions/@jupyterlab-examples/hello-world/static/third-party-licenses.json
jupyterlab_examples_hello_world-0.1.0.dist-info/METADATA
jupyterlab_examples_hello_world-0.1.0.dist-info/WHEEL
jupyterlab_examples_hello_world-0.1.0.dist-info/top_level.txt
jupyterlab_examples_hello_world-0.1.0.dist-info/RECORD
